ae/django_utils.py
ae_django_utils-0.3.2.dist-info/LICENSE.md
ae_django_utils-0.3.2.dist-info/METADATA
ae_django_utils-0.3.2.dist-info/WHEEL
ae_django_utils-0.3.2.dist-info/top_level.txt
ae_django_utils-0.3.2.dist-info/zip-safe
ae_django_utils-0.3.2.dist-info/RECORD
